{
    "session_id": "compile_694fd4ff56b7c7.31936205",
    "success": true,
    "stages": [
        {
            "name": "Lexical Analysis",
            "status": "completed",
            "duration": 65,
            "tokens": [
                {
                    "type": "IDENTIFIER",
                    "value": "#include",
                    "line": 1
                },
                {
                    "type": "IDENTIFIER",
                    "value": "<",
                    "line": 1
                },
                {
                    "type": "IDENTIFIER",
                    "value": "stdio.h",
                    "line": 1
                },
                {
                    "type": "IDENTIFIER",
                    "value": ">",
                    "line": 1
                },
                {
                    "type": "KEYWORD",
                    "value": "int",
                    "line": 3
                },
                {
                    "type": "KEYWORD",
                    "value": "main",
                    "line": 3
                },
                {
                    "type": "IDENTIFIER",
                    "value": "(",
                    "line": 3
                },
                {
                    "type": "IDENTIFIER",
                    "value": ")",
                    "line": 3
                },
                {
                    "type": "IDENTIFIER",
                    "value": "{",
                    "line": 3
                },
                {
                    "type": "KEYWORD",
                    "value": "int",
                    "line": 4
                },
                {
                    "type": "IDENTIFIER",
                    "value": "m",
                    "line": 4
                },
                {
                    "type": "IDENTIFIER",
                    "value": "=",
                    "line": 4
                },
                {
                    "type": "LITERAL",
                    "value": "50",
                    "line": 4
                },
                {
                    "type": "IDENTIFIER",
                    "value": ";",
                    "line": 4
                },
                {
                    "type": "KEYWORD",
                    "value": "printf",
                    "line": 5
                },
                {
                    "type": "IDENTIFIER",
                    "value": "(",
                    "line": 5
                },
                {
                    "type": "STRING_LITERAL",
                    "value": "\"Value",
                    "line": 5
                },
                {
                    "type": "IDENTIFIER",
                    "value": "of",
                    "line": 5
                },
                {
                    "type": "IDENTIFIER",
                    "value": "x:",
                    "line": 5
                },
                {
                    "type": "STRING_LITERAL",
                    "value": "%d\\n\",",
                    "line": 5
                },
                {
                    "type": "IDENTIFIER",
                    "value": "m",
                    "line": 5
                },
                {
                    "type": "IDENTIFIER",
                    "value": ")",
                    "line": 5
                },
                {
                    "type": "IDENTIFIER",
                    "value": ";",
                    "line": 5
                },
                {
                    "type": "KEYWORD",
                    "value": "return",
                    "line": 7
                },
                {
                    "type": "LITERAL",
                    "value": "0",
                    "line": 7
                },
                {
                    "type": "IDENTIFIER",
                    "value": ";",
                    "line": 7
                },
                {
                    "type": "IDENTIFIER",
                    "value": "}",
                    "line": 8
                }
            ]
        },
        {
            "name": "Syntax Analysis",
            "status": "completed",
            "duration": 295,
            "ast": {
                "type": "Program",
                "body": [
                    {
                        "type": "FunctionDeclaration",
                        "name": "main",
                        "params": [],
                        "body": [
                            {
                                "type": "VariableDeclaration",
                                "declarations": [
                                    {
                                        "type": "Identifier",
                                        "name": "a",
                                        "init": {
                                            "type": "Literal",
                                            "value": 5
                                        }
                                    },
                                    {
                                        "type": "Identifier",
                                        "name": "b",
                                        "init": {
                                            "type": "Literal",
                                            "value": 10
                                        }
                                    },
                                    {
                                        "type": "Identifier",
                                        "name": "sum",
                                        "init": {
                                            "type": "BinaryExpression",
                                            "operator": "+",
                                            "left": {
                                                "type": "Identifier",
                                                "name": "a"
                                            },
                                            "right": {
                                                "type": "Identifier",
                                                "name": "b"
                                            }
                                        }
                                    }
                                ]
                            }
                        ]
                    }
                ]
            }
        },
        {
            "name": "Semantic Analysis",
            "status": "completed",
            "duration": 125,
            "symbol_table": {
                "global": [
                    {
                        "name": "main",
                        "type": "function",
                        "return_type": "int"
                    }
                ],
                "main": [
                    {
                        "name": "a",
                        "type": "int"
                    },
                    {
                        "name": "b",
                        "type": "int"
                    },
                    {
                        "name": "sum",
                        "type": "int"
                    }
                ]
            }
        },
        {
            "name": "IR Generation",
            "status": "completed",
            "duration": 314,
            "ir_code": [
                {
                    "op": "ALLOC",
                    "dest": "a",
                    "type": "int"
                },
                {
                    "op": "ALLOC",
                    "dest": "b",
                    "type": "int"
                },
                {
                    "op": "ALLOC",
                    "dest": "sum",
                    "type": "int"
                },
                {
                    "op": "STORE",
                    "dest": "a",
                    "value": 5
                },
                {
                    "op": "STORE",
                    "dest": "b",
                    "value": 10
                },
                {
                    "op": "LOAD",
                    "dest": "t1",
                    "src": "a"
                },
                {
                    "op": "LOAD",
                    "dest": "t2",
                    "src": "b"
                },
                {
                    "op": "ADD",
                    "dest": "sum",
                    "src1": "t1",
                    "src2": "t2"
                }
            ]
        },
        {
            "name": "Optimization",
            "status": "completed",
            "duration": 417,
            "optimizations": {
                "constant_folding": true,
                "common_subexpression": true
            }
        },
        {
            "name": "Code Generation",
            "status": "completed",
            "duration": 268,
            "assembly": [
                ".section .text",
                ".globl main",
                "main:",
                "    push %rbp",
                "    mov %rsp, %rbp",
                "    sub $16, %rsp",
                "    movl $5, -4(%rbp)    # a = 5",
                "    movl $10, -8(%rbp)   # b = 10",
                "    movl -4(%rbp), %eax",
                "    addl -8(%rbp), %eax",
                "    movl %eax, -12(%rbp) # sum = a + b",
                "    movl $0, %eax",
                "    leave",
                "    ret"
            ]
        }
    ],
    "outputs": {
        "tokens": [
            {
                "type": "IDENTIFIER",
                "value": "#include",
                "line": 1
            },
            {
                "type": "IDENTIFIER",
                "value": "<",
                "line": 1
            },
            {
                "type": "IDENTIFIER",
                "value": "stdio.h",
                "line": 1
            },
            {
                "type": "IDENTIFIER",
                "value": ">",
                "line": 1
            },
            {
                "type": "KEYWORD",
                "value": "int",
                "line": 3
            },
            {
                "type": "KEYWORD",
                "value": "main",
                "line": 3
            },
            {
                "type": "IDENTIFIER",
                "value": "(",
                "line": 3
            },
            {
                "type": "IDENTIFIER",
                "value": ")",
                "line": 3
            },
            {
                "type": "IDENTIFIER",
                "value": "{",
                "line": 3
            },
            {
                "type": "KEYWORD",
                "value": "int",
                "line": 4
            },
            {
                "type": "IDENTIFIER",
                "value": "m",
                "line": 4
            },
            {
                "type": "IDENTIFIER",
                "value": "=",
                "line": 4
            },
            {
                "type": "LITERAL",
                "value": "50",
                "line": 4
            },
            {
                "type": "IDENTIFIER",
                "value": ";",
                "line": 4
            },
            {
                "type": "KEYWORD",
                "value": "printf",
                "line": 5
            },
            {
                "type": "IDENTIFIER",
                "value": "(",
                "line": 5
            },
            {
                "type": "STRING_LITERAL",
                "value": "\"Value",
                "line": 5
            },
            {
                "type": "IDENTIFIER",
                "value": "of",
                "line": 5
            },
            {
                "type": "IDENTIFIER",
                "value": "x:",
                "line": 5
            },
            {
                "type": "STRING_LITERAL",
                "value": "%d\\n\",",
                "line": 5
            },
            {
                "type": "IDENTIFIER",
                "value": "m",
                "line": 5
            },
            {
                "type": "IDENTIFIER",
                "value": ")",
                "line": 5
            },
            {
                "type": "IDENTIFIER",
                "value": ";",
                "line": 5
            },
            {
                "type": "KEYWORD",
                "value": "return",
                "line": 7
            },
            {
                "type": "LITERAL",
                "value": "0",
                "line": 7
            },
            {
                "type": "IDENTIFIER",
                "value": ";",
                "line": 7
            },
            {
                "type": "IDENTIFIER",
                "value": "}",
                "line": 8
            }
        ],
        "ast": {
            "type": "Program",
            "body": [
                {
                    "type": "FunctionDeclaration",
                    "name": "main",
                    "params": [],
                    "body": [
                        {
                            "type": "VariableDeclaration",
                            "declarations": [
                                {
                                    "type": "Identifier",
                                    "name": "a",
                                    "init": {
                                        "type": "Literal",
                                        "value": 5
                                    }
                                },
                                {
                                    "type": "Identifier",
                                    "name": "b",
                                    "init": {
                                        "type": "Literal",
                                        "value": 10
                                    }
                                },
                                {
                                    "type": "Identifier",
                                    "name": "sum",
                                    "init": {
                                        "type": "BinaryExpression",
                                        "operator": "+",
                                        "left": {
                                            "type": "Identifier",
                                            "name": "a"
                                        },
                                        "right": {
                                            "type": "Identifier",
                                            "name": "b"
                                        }
                                    }
                                }
                            ]
                        }
                    ]
                }
            ]
        },
        "ir": [
            {
                "op": "ALLOC",
                "dest": "a",
                "type": "int"
            },
            {
                "op": "ALLOC",
                "dest": "b",
                "type": "int"
            },
            {
                "op": "ALLOC",
                "dest": "sum",
                "type": "int"
            },
            {
                "op": "STORE",
                "dest": "a",
                "value": 5
            },
            {
                "op": "STORE",
                "dest": "b",
                "value": 10
            },
            {
                "op": "LOAD",
                "dest": "t1",
                "src": "a"
            },
            {
                "op": "LOAD",
                "dest": "t2",
                "src": "b"
            },
            {
                "op": "ADD",
                "dest": "sum",
                "src1": "t1",
                "src2": "t2"
            }
        ],
        "asm": [
            ".section .text",
            ".globl main",
            "main:",
            "    push %rbp",
            "    mov %rsp, %rbp",
            "    sub $16, %rsp",
            "    movl $5, -4(%rbp)    # a = 5",
            "    movl $10, -8(%rbp)   # b = 10",
            "    movl -4(%rbp), %eax",
            "    addl -8(%rbp), %eax",
            "    movl %eax, -12(%rbp) # sum = a + b",
            "    movl $0, %eax",
            "    leave",
            "    ret"
        ]
    }
}